doitintl/docops/__init__.py
doitintl/docops/data/corpora/leeds.txt.gz
doitintl/docops/gitbook/__init__.py
doitintl/docops/gitbook/api.py
doitintl/docops/gitbook/cache.py
doitintl/docops/gitbook/cli/__init__.py
doitintl/docops/gitbook/exceptions.py
doitintl/docops/gloss/__init__.py
doitintl/docops/gloss/analyzers/__init__.py
doitintl/docops/gloss/analyzers/terms.py
doitintl/docops/gloss/cache.py
doitintl/docops/gloss/charset.py
doitintl/docops/gloss/cli/__init__.py
doitintl/docops/gloss/cli/terms.py
doitintl/docops/gloss/config.py
doitintl/docops/gloss/print.py
doitintl/docops/screenshots/__init__.py
doitintl/docops/screenshots/assets/frame.png
doitintl/docops/screenshots/cli/__init__.py
doitintl_docops-2.1.0.dist-info/entry_points.txt
doitintl_docops-2.1.0.dist-info/LICENSE
doitintl_docops-2.1.0.dist-info/WHEEL
doitintl_docops-2.1.0.dist-info/METADATA
doitintl_docops-2.1.0.dist-info/RECORD
